[
    {
        "object_named_as": "Parth Mehta",
        "series_ordinal": 1,
        "orcid_id": null,
        "affiliation_string": "Parmonic, Atlanta, USA"
    },
    {
        "object_named_as": "Thomas Mandl",
        "series_ordinal": 2,
        "orcid_id": null,
        "affiliation_string": "Universität Hildesheim, Hildesheim, Germany"
    },
    {
        "object_named_as": "Prasenjit Majumder",
        "series_ordinal": 3,
        "orcid_id": null,
        "affiliation_string": "Dhirubhai Ambani Institute of Information and Communication Technology, Gandhinagar, India"
    },
    {
        "object_named_as": "Mandar Mitra",
        "series_ordinal": 4,
        "orcid_id": null,
        "affiliation_string": "Indian Statistical Institute, Kolkata, India"
    }
]