[
    {
        "object_named_as": "Ramy Elmoazen",
        "series_ordinal": 1,
        "orcid_id": null,
        "affiliation_string": "School of Computing, University of Eastern Finland"
    },
    {
        "object_named_as": "Sonsoles López-Pernas",
        "series_ordinal": 2,
        "orcid_id": null,
        "affiliation_string": "Centre for the Science of Learning & Technology (SLATE), University of Bergen"
    },
    {
        "object_named_as": "Kamila Misiejuk",
        "series_ordinal": 3,
        "orcid_id": null,
        "affiliation_string": "Centre for the Science of Learning & Technology (SLATE), University of Bergen"
    },
    {
        "object_named_as": "Mohammad Khalil",
        "series_ordinal": 4,
        "orcid_id": null,
        "affiliation_string": "Centre for the Science of Learning & Technology (SLATE), University of Bergen"
    },
    {
        "object_named_as": "Barbara Wasson",
        "series_ordinal": 5,
        "orcid_id": null,
        "affiliation_string": "Centre for the Science of Learning & Technology (SLATE), University of Bergen"
    },
    {
        "object_named_as": "Mohammed Saqr",
        "series_ordinal": 6,
        "orcid_id": null,
        "affiliation_string": "School of Computing, University of Eastern Finland"
    }
]